[
  {
    "CardName": "Dark Mambele",
    "CardID": "9932"
  },
  {
    "CardName": "Dark Master - Zorc",
    "CardID": "5782"
  },
  {
    "CardName": "Dark Mimic LV1",
    "CardID": "6101"
  },
  {
    "CardName": "Dark Mimic LV3",
    "CardID": "6102"
  },
  {
    "CardName": "Dark Mirror Force",
    "CardID": "5858"
  },
  {
    "CardName": "Dark Necrofear",
    "CardID": "5222"
  },
  {
    "CardName": "Dark Nephthys",
    "CardID": "7420"
  },
  {
    "CardName": "Dark Paladin",
    "CardID": "5628"
  },
  {
    "CardName": "Dark Prisoner",
    "CardID": "4179"
  },
  {
    "CardName": "Dark Rabbit",
    "CardID": "4390"
  },
  {
    "CardName": "Dark Rebellion Xyz Dragon",
    "CardID": "11385"
  },
  {
    "CardName": "Dark Red Enchanter",
    "CardID": "6555"
  },
  {
    "CardName": "Dark Renewal",
    "CardID": "4822"
  },
  {
    "CardName": "Dark Requiem Xyz Dragon",
    "CardID": "12639"
  },
  {
    "CardName": "Dark Resonator",
    "CardID": "7708"
  },
  {
    "CardName": "Dark Room of Nightmare",
    "CardID": "5531"
  },
  {
    "CardName": "Dark Rose Fairy",
    "CardID": "14176"
  },
  {
    "CardName": "Dark Ruler Ha Des",
    "CardID": "5301"
  },
  {
    "CardName": "Dark Ruler No More",
    "CardID": "14742"
  },
  {
    "CardName": "Dark Sacrifice",
    "CardID": "14377"
  },
  {
    "CardName": "Dark Sage",
    "CardID": "5230"
  },
  {
    "CardName": "Dark Sanctuary",
    "CardID": "12572"
  },
  {
    "CardName": "Dark Scheme",
    "CardID": "9716"
  },
  {
    "CardName": "Dark Scorpion - Chick the Yellow",
    "CardID": "5718"
  },
  {
    "CardName": "Dark Scorpion - Cliff the Trap Remover",
    "CardID": "5662"
  },
  {
    "CardName": "Dark Scorpion - Gorg the Strong",
    "CardID": "5765"
  },
  {
    "CardName": "Dark Scorpion - Meanae the Thorn",
    "CardID": "5766"
  },
  {
    "CardName": "Dark Scorpion Burglars",
    "CardID": "5425"
  },
  {
    "CardName": "Dark Scorpion Combination",
    "CardID": "5795"
  },
  {
    "CardName": "Dark Simorgh",
    "CardID": "7770"
  },
  {
    "CardName": "Dark Smog",
    "CardID": "9872"
  },
  {
    "CardName": "Dark Snake Syndrome",
    "CardID": "5536"
  },
  {
    "CardName": "Dark Spell Regeneration",
    "CardID": "5638"
  },
  {
    "CardName": "Dark Spider",
    "CardID": "8450"
  },
  {
    "CardName": "Dark Spirit Art - Greed",
    "CardID": "7469"
  },
  {
    "CardName": "Dark Spirit of Banishment",
    "CardID": "14582"
  },
  {
    "CardName": "Dark Spirit of Malice",
    "CardID": "14583"
  },
  {
    "CardName": "Dark Spirit of the Silent",
    "CardID": "5227"
  },
  {
    "CardName": "Dark Spirit's Mastery",
    "CardID": "14584"
  },
  {
    "CardName": "Dark Strike Fighter",
    "CardID": "8035"
  },
  {
    "CardName": "Dark Summoning Beast",
    "CardID": "12903"
  },
  {
    "CardName": "Dark Templar @Ignister",
    "CardID": "14854"
  },
  {
    "CardName": "Dark Tinker",
    "CardID": "8010"
  },
  {
    "CardName": "Dark Titan of Terror",
    "CardID": "4239"
  },
  {
    "CardName": "Dark Valkyria",
    "CardID": "7600"
  },
  {
    "CardName": "Dark Verger",
    "CardID": "8157"
  },
  {
    "CardName": "Dark Voltanis",
    "CardID": "8139"
  },
  {
    "CardName": "Dark Witch",
    "CardID": "4588"
  },
  {
    "CardName": "Dark World Accession",
    "CardID": "17989"
  },
  {
    "CardName": "Dark World Archives",
    "CardID": "17986"
  },
  {
    "CardName": "Dark World Brainwashing",
    "CardID": "13113"
  },
  {
    "CardName": "Dark World Dealings",
    "CardID": "7002"
  },
  {
    "CardName": "Dark World Grimoire",
    "CardID": "7461"
  },
  {
    "CardName": "Dark World Lightning",
    "CardID": "6512"
  },
  {
    "CardName": "Dark World Punishment",
    "CardID": "17987"
  },
  {
    "CardName": "Dark World Puppetry",
    "CardID": "17985"
  },
  {
    "CardName": "Dark Zebra",
    "CardID": "4920"
  },
  {
    "CardName": "Dark-Eyes Illusionist",
    "CardID": "4736"
  },
  {
    "CardName": "Dark-Piercing Light",
    "CardID": "4356"
  },
  {
    "CardName": "Darkbishop Archfiend",
    "CardID": "5774"
  },
  {
    "CardName": "Darkblaze Dragon",
    "CardID": "7245"
  },
  {
    "CardName": "Darkest Diabolos, Lord of the Lair",
    "CardID": "13683"
  },
  {
    "CardName": "Darkfall (Updated from: Dark Trap Hole)",
    "CardID": "9157"
  },
  {
    "CardName": "Darkfire Dragon",
    "CardID": "4174"
  },
  {
    "CardName": "Darkfire Soldier #1",
    "CardID": "4973"
  },
  {
    "CardName": "Darkfire Soldier #2",
    "CardID": "4975"
  },
  {
    "CardName": "Darkflare Dragon",
    "CardID": "9956"
  },
  {
    "CardName": "Darklight",
    "CardID": "9793"
  },
  {
    "CardName": "Darklon",
    "CardID": "9876"
  },
  {
    "CardName": "Darklord Amdusc",
    "CardID": "12727"
  },
  {
    "CardName": "Darklord Asmodeus",
    "CardID": "8287"
  },
  {
    "CardName": "Darklord Contact",
    "CardID": "12729"
  },
  {
    "CardName": "Darklord Descent",
    "CardID": "8286"
  },
  {
    "CardName": "Darklord Desire",
    "CardID": "8386"
  },
  {
    "CardName": "Darklord Edeh Arae",
    "CardID": "8289"
  },
  {
    "CardName": "Darklord Enchantment",
    "CardID": "12731"
  },
  {
    "CardName": "Darklord Ixchel",
    "CardID": "12724"
  },
  {
    "CardName": "Darklord Marie (Updated from: Marie the Fallen One)",
    "CardID": "5209"
  },
  {
    "CardName": "Darklord Morningstar",
    "CardID": "12723"
  },
  {
    "CardName": "Darklord Nasten",
    "CardID": "12726"
  },
  {
    "CardName": "Darklord Nergal",
    "CardID": "15259"
  },
  {
    "CardName": "Darklord Nurse Reficule (Updated from: Nurse Reficule the Fallen One)",
    "CardID": "7352"
  },
  {
    "CardName": "Darklord Rebellion",
    "CardID": "12730"
  },
  {
    "CardName": "Darklord Superbia",
    "CardID": "8288"
  },
  {
    "CardName": "Darklord Tezcatlipoca",
    "CardID": "12725"
  },
  {
    "CardName": "Darklord Ukoback",
    "CardID": "8384"
  },
  {
    "CardName": "Darklord Uprising",
    "CardID": "15309"
  },
  {
    "CardName": "Darklord Zerato",
    "CardID": "7562"
  },
  {
    "CardName": "Darkness Approaches",
    "CardID": "4902"
  },
  {
    "CardName": "Darkness Destroyer",
    "CardID": "7983"
  },
  {
    "CardName": "Darkness Metal, the Dragon of Dark Steel",
    "CardID": "13971"
  },
  {
    "CardName": "Darkness Neosphere",
    "CardID": "8537"
  },
  {
    "CardName": "Darknight Parshath",
    "CardID": "7563"
  },
  {
    "CardName": "Darksea Float",
    "CardID": "8305"
  },
  {
    "CardName": "Darksea Rescue",
    "CardID": "8304"
  },
  {
    "CardName": "Darkstorm Dragon",
    "CardID": "9911"
  },
  {
    "CardName": "Darktellarknight Batlamyus",
    "CardID": "12641"
  },
  {
    "CardName": "Darkworld Shackles",
    "CardID": "9134"
  },
  {
    "CardName": "Darkworld Thorns",
    "CardID": "4573"
  },
  {
    "CardName": "Darton the Mechanical Monstrosity",
    "CardID": "16838"
  }
]