[
  {
    "CardName": "Hypnocorn",
    "CardID": "8949"
  },
  {
    "CardName": "Hypnosister",
    "CardID": "11252"
  },
  {
    "CardName": "Hysteric Fairy",
    "CardID": "5205"
  },
  {
    "CardName": "Hysteric Party",
    "CardID": "6722"
  },
  {
    "CardName": "Hysteric Sign",
    "CardID": "10546"
  },
  {
    "CardName": "I:P Masquerena",
    "CardID": "14676"
  },
  {
    "CardName": "Ib the World Chalice Justiciar",
    "CardID": "14285"
  },
  {
    "CardName": "Ib the World Chalice Priestess",
    "CardID": "13087"
  },
  {
    "CardName": "Ibicella Lutea",
    "CardID": "14836"
  },
  {
    "CardName": "Icarus Attack",
    "CardID": "6709"
  },
  {
    "CardName": "Ice Barrier",
    "CardID": "8885"
  },
  {
    "CardName": "Ice Beast Zerofyne",
    "CardID": "10530"
  },
  {
    "CardName": "Ice Dragon's Prison",
    "CardID": "15313"
  },
  {
    "CardName": "Ice Hand",
    "CardID": "11191"
  },
  {
    "CardName": "Ice Knight",
    "CardID": "6861"
  },
  {
    "CardName": "Ice Master",
    "CardID": "7025"
  },
  {
    "CardName": "Ice Mirror",
    "CardID": "16418"
  },
  {
    "CardName": "Ice Princess Zereort",
    "CardID": "10655"
  },
  {
    "CardName": "Ice Queen",
    "CardID": "7498"
  },
  {
    "CardName": "Icejade Acti",
    "CardID": "16494"
  },
  {
    "CardName": "Icejade Aegirine",
    "CardID": "16812"
  },
  {
    "CardName": "Icejade Cenote Enion Cradle",
    "CardID": "16857"
  },
  {
    "CardName": "Icejade Cradle",
    "CardID": "16542"
  },
  {
    "CardName": "Icejade Creation Aegirocassis",
    "CardID": "17412"
  },
  {
    "CardName": "Icejade Creation Kingfisher",
    "CardID": "16813"
  },
  {
    "CardName": "Icejade Curse",
    "CardID": "17167"
  },
  {
    "CardName": "Icejade Erosion",
    "CardID": "16871"
  },
  {
    "CardName": "Icejade Gymir Aegirine",
    "CardID": "18183"
  },
  {
    "CardName": "Icejade Kosmochlor",
    "CardID": "16811"
  },
  {
    "CardName": "Icejade Manifestation",
    "CardID": "18198"
  },
  {
    "CardName": "Icejade Ran Aegirine",
    "CardID": "18473"
  },
  {
    "CardName": "Icejade Tinola",
    "CardID": "16495"
  },
  {
    "CardName": "Icejade Tremora",
    "CardID": "16496"
  },
  {
    "CardName": "Ichiroku's Ledger Book",
    "CardID": "17189"
  },
  {
    "CardName": "Icy Breeze Refrain",
    "CardID": "15763"
  },
  {
    "CardName": "Icy Crevasse",
    "CardID": "9787"
  },
  {
    "CardName": "Idaten the Conqueror Star",
    "CardID": "13832"
  },
  {
    "CardName": "Ido the Supreme Magical Force",
    "CardID": "8087"
  },
  {
    "CardName": "Igknight Burst",
    "CardID": "11857"
  },
  {
    "CardName": "Igknight Cavalier",
    "CardID": "11974"
  },
  {
    "CardName": "Igknight Champion",
    "CardID": "11817"
  },
  {
    "CardName": "Igknight Crusader",
    "CardID": "11811"
  },
  {
    "CardName": "Igknight Gallant",
    "CardID": "11815"
  },
  {
    "CardName": "Igknight Lancer",
    "CardID": "11816"
  },
  {
    "CardName": "Igknight Margrave",
    "CardID": "11814"
  },
  {
    "CardName": "Igknight Paladin",
    "CardID": "11813"
  },
  {
    "CardName": "Igknight Reload",
    "CardID": "12005"
  },
  {
    "CardName": "Igknight Squire",
    "CardID": "11810"
  },
  {
    "CardName": "Igknight Templar",
    "CardID": "11812"
  },
  {
    "CardName": "Igknight Veteran",
    "CardID": "11975"
  },
  {
    "CardName": "Igknights Unite",
    "CardID": "12651"
  },
  {
    "CardName": "Ignis Heat, the True Dracowarrior",
    "CardID": "12935"
  },
  {
    "CardName": "Ignis Phoenix, the Dracoslayer",
    "CardID": "17778"
  },
  {
    "CardName": "Ignister A.I.Land",
    "CardID": "14859"
  },
  {
    "CardName": "Ignister Prominence, the Blasting Dracoslayer",
    "CardID": "11834"
  },
  {
    "CardName": "Ignition Beast Volcannon",
    "CardID": "9195"
  },
  {
    "CardName": "Ignition Phoenix",
    "CardID": "11845"
  },
  {
    "CardName": "Ignoble Knight of Black Laundsallyn",
    "CardID": "10350"
  },
  {
    "CardName": "Ignoble Knight of High Laundsallyn",
    "CardID": "10877"
  },
  {
    "CardName": "Ikelos, the Dream Mirror Mara",
    "CardID": "14715"
  },
  {
    "CardName": "Ikelos, the Dream Mirror Sprite",
    "CardID": "14714"
  },
  {
    "CardName": "Il Blud",
    "CardID": "7340"
  },
  {
    "CardName": "Illegal Knight",
    "CardID": "17135"
  },
  {
    "CardName": "Illusion Balloons",
    "CardID": "11573"
  },
  {
    "CardName": "Illusion Magic",
    "CardID": "12457"
  },
  {
    "CardName": "Illusion of Chaos",
    "CardID": "16839"
  },
  {
    "CardName": "Illusionist Faceless Mage",
    "CardID": "4048"
  },
  {
    "CardName": "Illusionist Faceless Magician",
    "CardID": "13465"
  },
  {
    "CardName": "Illusory Snatcher",
    "CardID": "10167"
  },
  {
    "CardName": "Imairuka",
    "CardID": "10315"
  },
  {
    "CardName": "Imduk the World Chalice Dragon",
    "CardID": "13086"
  },
  {
    "CardName": "Immortal Dragon",
    "CardID": "17152"
  },
  {
    "CardName": "Immortal Phoenix Gearfried",
    "CardID": "14801"
  },
  {
    "CardName": "Immortal Ruler",
    "CardID": "8373"
  },
  {
    "CardName": "Impcantation Bookstone",
    "CardID": "13911"
  },
  {
    "CardName": "Impcantation Candoll",
    "CardID": "13732"
  },
  {
    "CardName": "Impcantation Chalislime",
    "CardID": "14109"
  },
  {
    "CardName": "Impcantation Inception",
    "CardID": "14142"
  },
  {
    "CardName": "Impcantation Penciplume",
    "CardID": "13910"
  },
  {
    "CardName": "Impcantation Talismandra",
    "CardID": "13733"
  },
  {
    "CardName": "Impcantation Thanatosis",
    "CardID": "14312"
  },
  {
    "CardName": "Impenetrable Attack",
    "CardID": "10196"
  },
  {
    "CardName": "Impenetrable Formation",
    "CardID": "6355"
  },
  {
    "CardName": "Imperial Bower",
    "CardID": "16479"
  },
  {
    "CardName": "Imperial Custom",
    "CardID": "8357"
  },
  {
    "CardName": "Imperial Iron Wall",
    "CardID": "7858"
  },
  {
    "CardName": "Imperial Order",
    "CardID": "4960"
  },
  {
    "CardName": "Imperial Princess Quinquery",
    "CardID": "18667"
  },
  {
    "CardName": "Imperial Tombs of Necrovalley",
    "CardID": "10962"
  },
  {
    "CardName": "Imperion Magnum the Superconductive Battlebot",
    "CardID": "12581"
  },
  {
    "CardName": "Imprisoned Queen Archfiend",
    "CardID": "7370"
  },
  {
    "CardName": "Imprudent Intrusion",
    "CardID": "16884"
  },
  {
    "CardName": "Inaba White Rabbit",
    "CardID": "5374"
  },
  {
    "CardName": "Inari Fire",
    "CardID": "10397"
  },
  {
    "CardName": "Incandescent Ordeal",
    "CardID": "5783"
  },
  {
    "CardName": "Incarnated Machine Angel",
    "CardID": "14173"
  },
  {
    "CardName": "Incredible Ecclesia, the Virtuous",
    "CardID": "16493"
  },
  {
    "CardName": "Indiora Doom Volt the Cubic Emperor",
    "CardID": "12521"
  },
  {
    "CardName": "Indomitable Fighter Lei Lei",
    "CardID": "6421"
  },
  {
    "CardName": "Indomitable Gladiator Beast",
    "CardID": "8051"
  }
]