[
  {
    "CardName": "Different Dimension Deepsea Trench",
    "CardID": "10274"
  },
  {
    "CardName": "Different Dimension Dragon",
    "CardID": "5696"
  },
  {
    "CardName": "Different Dimension Encounter",
    "CardID": "11412"
  },
  {
    "CardName": "Different Dimension Gate",
    "CardID": "5736"
  },
  {
    "CardName": "Different Dimension Ground",
    "CardID": "9154"
  },
  {
    "CardName": "Diffusion Wave-Motion",
    "CardID": "5631"
  },
  {
    "CardName": "Dig Beak",
    "CardID": "4165"
  },
  {
    "CardName": "Dig of Destiny",
    "CardID": "12505"
  },
  {
    "CardName": "Digit Jamming",
    "CardID": "17470"
  },
  {
    "CardName": "Digital Bug Centibit",
    "CardID": "12306"
  },
  {
    "CardName": "Digital Bug Cocoondenser",
    "CardID": "12305"
  },
  {
    "CardName": "Digital Bug Corebage",
    "CardID": "12327"
  },
  {
    "CardName": "Digital Bug LEDybug",
    "CardID": "12943"
  },
  {
    "CardName": "Digital Bug Registrider",
    "CardID": "15714"
  },
  {
    "CardName": "Digital Bug Rhinosebus",
    "CardID": "12328"
  },
  {
    "CardName": "Digital Bug Scaradiator",
    "CardID": "12326"
  },
  {
    "CardName": "Digital Bug Websolder",
    "CardID": "12307"
  },
  {
    "CardName": "Digitron",
    "CardID": "13192"
  },
  {
    "CardName": "Digvorzhak, King of Heavy Industry",
    "CardID": "9962"
  },
  {
    "CardName": "Dillingerous Dragon",
    "CardID": "14291"
  },
  {
    "CardName": "Dimension Conjurer",
    "CardID": "16807"
  },
  {
    "CardName": "Dimension Dice",
    "CardID": "17624"
  },
  {
    "CardName": "Dimension Distortion",
    "CardID": "5848"
  },
  {
    "CardName": "Dimension Explosion",
    "CardID": "7450"
  },
  {
    "CardName": "Dimension Fortress Weapon",
    "CardID": "8028"
  },
  {
    "CardName": "Dimension Fusion",
    "CardID": "5906"
  },
  {
    "CardName": "Dimension Fusion Destruction",
    "CardID": "15144"
  },
  {
    "CardName": "Dimension Gate",
    "CardID": "10427"
  },
  {
    "CardName": "Dimension Guardian",
    "CardID": "12507"
  },
  {
    "CardName": "Dimension Jar",
    "CardID": "5597"
  },
  {
    "CardName": "Dimension Mirage",
    "CardID": "12508"
  },
  {
    "CardName": "Dimension Reflector",
    "CardID": "12504"
  },
  {
    "CardName": "Dimension Shifter",
    "CardID": "14740"
  },
  {
    "CardName": "Dimension Slice",
    "CardID": "10099"
  },
  {
    "CardName": "Dimension Sphinx",
    "CardID": "12506"
  },
  {
    "CardName": "Dimension Wall",
    "CardID": "6448"
  },
  {
    "CardName": "Dimension Wanderer",
    "CardID": "10337"
  },
  {
    "CardName": "Dimensional Alchemist",
    "CardID": "7517"
  },
  {
    "CardName": "Dimensional Allotrope Varis",
    "CardID": "18173"
  },
  {
    "CardName": "Dimensional Barrier",
    "CardID": "12668"
  },
  {
    "CardName": "Dimensional Fissure",
    "CardID": "6707"
  },
  {
    "CardName": "Dimensional Inversion",
    "CardID": "6913"
  },
  {
    "CardName": "Dimensional Prison",
    "CardID": "7400"
  },
  {
    "CardName": "Dimensionhole",
    "CardID": "5132"
  },
  {
    "CardName": "Dimer Synthesis",
    "CardID": "16253"
  },
  {
    "CardName": "Dingirsu, the Orcust of the Evening Star",
    "CardID": "14288"
  },
  {
    "CardName": "Dino-Sewing",
    "CardID": "11876"
  },
  {
    "CardName": "Dinomic Powerload",
    "CardID": "12170"
  },
  {
    "CardName": "Dinomight Knight, the True Dracofighter",
    "CardID": "12936"
  },
  {
    "CardName": "Dinomight Powerload, the Dracoslayer",
    "CardID": "17780"
  },
  {
    "CardName": "Dinomist Ankylos",
    "CardID": "12425"
  },
  {
    "CardName": "Dinomist Brachion",
    "CardID": "12135"
  },
  {
    "CardName": "Dinomist Ceratops",
    "CardID": "12136"
  },
  {
    "CardName": "Dinomist Charge",
    "CardID": "12171"
  },
  {
    "CardName": "Dinomist Eruption",
    "CardID": "12345"
  },
  {
    "CardName": "Dinomist Plesios",
    "CardID": "12133"
  },
  {
    "CardName": "Dinomist Pteran",
    "CardID": "12134"
  },
  {
    "CardName": "Dinomist Rex",
    "CardID": "12137"
  },
  {
    "CardName": "Dinomist Rush",
    "CardID": "12181"
  },
  {
    "CardName": "Dinomist Spinos",
    "CardID": "12304"
  },
  {
    "CardName": "Dinomist Stegosaur",
    "CardID": "12132"
  },
  {
    "CardName": "Dinomists Howling",
    "CardID": "12990"
  },
  {
    "CardName": "Dinomorphia Alert",
    "CardID": "16874"
  },
  {
    "CardName": "Dinomorphia Brute",
    "CardID": "16875"
  },
  {
    "CardName": "Dinomorphia Diplos",
    "CardID": "16815"
  },
  {
    "CardName": "Dinomorphia Domain",
    "CardID": "16873"
  },
  {
    "CardName": "Dinomorphia Frenzy",
    "CardID": "17188"
  },
  {
    "CardName": "Dinomorphia Intact",
    "CardID": "18539"
  },
  {
    "CardName": "Dinomorphia Kentregina",
    "CardID": "16843"
  },
  {
    "CardName": "Dinomorphia Reversion",
    "CardID": "16878"
  },
  {
    "CardName": "Dinomorphia Rexterm",
    "CardID": "17149"
  },
  {
    "CardName": "Dinomorphia Shell",
    "CardID": "16876"
  },
  {
    "CardName": "Dinomorphia Sonic",
    "CardID": "16877"
  },
  {
    "CardName": "Dinomorphia Stealthbergia",
    "CardID": "16844"
  },
  {
    "CardName": "Dinomorphia Therizia",
    "CardID": "16814"
  },
  {
    "CardName": "Dinoster Power, the Mighty Dracoslayer",
    "CardID": "12154"
  },
  {
    "CardName": "Dinowrestler Capaptera",
    "CardID": "13893"
  },
  {
    "CardName": "Dinowrestler Capoeiraptor",
    "CardID": "13894"
  },
  {
    "CardName": "Dinowrestler Chimera T Wrextle",
    "CardID": "14280"
  },
  {
    "CardName": "Dinowrestler Coelasilat",
    "CardID": "14257"
  },
  {
    "CardName": "Dinowrestler Eskrimamenchi",
    "CardID": "14256"
  },
  {
    "CardName": "Dinowrestler Giga Spinosavate",
    "CardID": "14284"
  },
  {
    "CardName": "Dinowrestler Iguanodraka",
    "CardID": "14790"
  },
  {
    "CardName": "Dinowrestler King T Wrextle",
    "CardID": "13928"
  },
  {
    "CardName": "Dinowrestler Martial Ampelo",
    "CardID": "14633"
  },
  {
    "CardName": "Dinowrestler Martial Anga",
    "CardID": "14258"
  },
  {
    "CardName": "Dinowrestler Martial Ankylo",
    "CardID": "14454"
  },
  {
    "CardName": "Dinowrestler Pankratops",
    "CardID": "13896"
  },
  {
    "CardName": "Dinowrestler Rambrachio",
    "CardID": "14455"
  },
  {
    "CardName": "Dinowrestler Systegosaur",
    "CardID": "13895"
  },
  {
    "CardName": "Dinowrestler Terra Parkourio",
    "CardID": "14292"
  },
  {
    "CardName": "Dinowrestler Valeonyx",
    "CardID": "14634"
  },
  {
    "CardName": "Diplexer Chimera",
    "CardID": "13925"
  },
  {
    "CardName": "Dirge of the Lost Dragon",
    "CardID": "14313"
  },
  {
    "CardName": "Disappear",
    "CardID": "5397"
  },
  {
    "CardName": "Disarm",
    "CardID": "7320"
  },
  {
    "CardName": "Disarmament",
    "CardID": "5683"
  },
  {
    "CardName": "Disc Fighter",
    "CardID": "5970"
  },
  {
    "CardName": "Disciple of Nephthys",
    "CardID": "14010"
  },
  {
    "CardName": "Disciple of the Forbidden Spell",
    "CardID": "6594"
  }
]